CMakeLists.txt
MANIFEST.in
README.md
VERSION
knxmodule.cpp
setup.py
write_version_info.py
./CMakeLists.txt
./VERSION
./knxmodule.cpp
./setup.py
./write_version_info.py
../README.md
../src/esp_platform.cpp
../src/esp_platform.h
../src/knx.h
../src/knx_facade.cpp
../src/knx_facade.h
../src/linux_platform.cpp
../src/linux_platform.h
../src/samd_platform.cpp
../src/samd_platform.h
../src/knx/address_table_object.cpp
../src/knx/address_table_object.h
../src/knx/apdu.cpp
../src/knx/apdu.h
../src/knx/application_layer.cpp
../src/knx/application_layer.h
../src/knx/application_program_object.cpp
../src/knx/application_program_object.h
../src/knx/association_table_object.cpp
../src/knx/association_table_object.h
../src/knx/bau.cpp
../src/knx/bau.h
../src/knx/bau07B0.cpp
../src/knx/bau07B0.h
../src/knx/bau57B0.cpp
../src/knx/bau57B0.h
../src/knx/bau_systemB.cpp
../src/knx/bau_systemB.h
../src/knx/bits.cpp
../src/knx/bits.h
../src/knx/cemi_frame.cpp
../src/knx/cemi_frame.h
../src/knx/data_link_layer.cpp
../src/knx/data_link_layer.h
../src/knx/datapoint_types.cpp
../src/knx/datapoint_types.h
../src/knx/device_object.cpp
../src/knx/device_object.h
../src/knx/dpt.cpp
../src/knx/dpt.h
../src/knx/dptconvert.cpp
../src/knx/dptconvert.h
../src/knx/group_object.cpp
../src/knx/group_object.h
../src/knx/group_object_table_object.cpp
../src/knx/group_object_table_object.h
../src/knx/interface_object.cpp
../src/knx/interface_object.h
../src/knx/ip_data_link_layer.cpp
../src/knx/ip_data_link_layer.h
../src/knx/ip_parameter_object.cpp
../src/knx/ip_parameter_object.h
../src/knx/knx_types.h
../src/knx/knx_value.cpp
../src/knx/knx_value.h
../src/knx/memory.cpp
../src/knx/memory.h
../src/knx/network_layer.cpp
../src/knx/network_layer.h
../src/knx/npdu.cpp
../src/knx/npdu.h
../src/knx/platform.cpp
../src/knx/platform.h
../src/knx/property_types.h
../src/knx/save_restore.h
../src/knx/table_object.cpp
../src/knx/table_object.h
../src/knx/tpdu.cpp
../src/knx/tpdu.h
knxPython.egg-info/PKG-INFO
knxPython.egg-info/SOURCES.txt
knxPython.egg-info/dependency_links.txt
knxPython.egg-info/not-zip-safe
knxPython.egg-info/top_level.txt
