Metadata-Version: 2.1
Name: knxPython
Version: 0.1.6
Summary: Lib to implement knx-devices
Home-page: https://github.com/thelsing/knx
Author: Thomas Kunze
Author-email: thomas.kunze@gmx.com
License: GPL3
Platform: UNKNOWN
